Metadata-Version: 1.1
Name: smallvectors
Version: 0.2.3
Summary: Efficient linear algebra in low dimensions
Home-page: https://github.com/fabiommendes/smallshapes
Author: Fábio Macêdo Mendes
Author-email: fabiomacedomendes@gmail.com
License: GPL
Platform: UNKNOWN
Classifier: Development Status :: 3 - Alpha
Classifier: Intended Audience :: Developers
Classifier: License :: OSI Approved :: GNU General Public License (GPL)
Classifier: Operating System :: POSIX
Classifier: Programming Language :: Python
Classifier: Topic :: Software Development :: Libraries
